pymask/__init__.py
pymask/annotator.py
pymask/cli.py
pmask-0.13.dist-info/LICENSE
pmask-0.13.dist-info/METADATA
pmask-0.13.dist-info/WHEEL
pmask-0.13.dist-info/entry_points.txt
pmask-0.13.dist-info/top_level.txt
pmask-0.13.dist-info/RECORD
