Metadata-Version: 2.1
Name: pmask
Version: 0.13
Summary: Dead simple image annotation tool to create binary mask via command line
Home-page: https://github.com/aGIToz/PyMask
Author: Amitoz Azad
License: MIT
License-File: LICENSE
Requires-Dist: opencv-python
Requires-Dist: numpy
